books/__init__.py
books/admin.py
books/apps.py
books/forms.py
books/models.py
books/tests.py
books/urls.py
books/views.py
books/migrations/0001_initial.py
books/migrations/__init__.py
books/templates/author_books_edit.html
books/templates/author_create.html
books/templates/author_detail.html
books/templates/author_list.html
books/templates/base.html
books/templates/home.html
mydjbooks-0.0.1.dist-info/LICENCE.txt
mydjbooks-0.0.1.dist-info/METADATA
mydjbooks-0.0.1.dist-info/WHEEL
mydjbooks-0.0.1.dist-info/top_level.txt
mydjbooks-0.0.1.dist-info/RECORD
