Metadata-Version: 2.1
Name: mydjbooks
Version: 0.0.1
Summary: A very basic django app
Home-page: https://www.abdulrahimk.com
Author: Abdul Rahim K
Author-email: abdulrahim.uj@gmail.com
License: MIT
Keywords: mydjbooks
Platform: UNKNOWN
Classifier: Environment :: Web Environment
Classifier: Framework :: Django
Classifier: Intended Audience :: Developers
Classifier: License :: OSI Approved :: MIT License
Classifier: Operating System :: OS Independent
Classifier: Programming Language :: Python :: 3
Classifier: Topic :: Software Development :: Libraries :: Python Modules
